python_kafka_logging
