Metadata-Version: 1.1
Name: python-kafka-logging
Version: 0.5
Summary: Simple python logging handler for forwarding logs to a kafka server.
Home-page: https://github.com/taykey/python-kafka-logging
Author: Taykey INC
Author-email: github@taykey.com
License: Apache 2.0
Keywords: python,logging,handler,example,kafka,logs,logstash,formatter
Platform: UNKNOWN
Classifier: Intended Audience :: Developers
Classifier: Natural Language :: English
Classifier: License :: OSI Approved :: Apache Software License
Classifier: Programming Language :: Python
Classifier: Programming Language :: Python :: 2.7
